ddg2json/__init__.py
ddg2json-0.1.3.dist-info/entry_points.txt
ddg2json-0.1.3.dist-info/WHEEL
ddg2json-0.1.3.dist-info/METADATA
ddg2json-0.1.3.dist-info/RECORD
