Metadata-Version: 2.1
Name: ddg2json
Version: 0.1.3
Summary: Parses scraped HTML of DuckDuckGo pages into JSON
License: MIT
Author: NightMachinary
Author-email: rudiwillalwaysloveyou@gmail.com
Requires-Python: >=3.7
Classifier: License :: OSI Approved :: MIT License
Classifier: Programming Language :: Python :: 3
Classifier: Programming Language :: Python :: 3.7
Classifier: Programming Language :: Python :: 3.8
Classifier: Programming Language :: Python :: 3.9
Requires-Dist: beautifulsoup4 (>=4.8)
